plectrum/__init__.py
plectrum/_version.py
plectrum/api.py
plectrum/application.py
plectrum/control.py
plectrum/selection.py
plectrum-0.1.0a0.dist-info/DESCRIPTION.rst
plectrum-0.1.0a0.dist-info/METADATA
plectrum-0.1.0a0.dist-info/RECORD
plectrum-0.1.0a0.dist-info/WHEEL
plectrum-0.1.0a0.dist-info/metadata.json
plectrum-0.1.0a0.dist-info/top_level.txt
