Metadata-Version: 2.0
Name: plectrum
Version: 0.1.0a0
Summary: Interactively select items from a list in a terminal.
Home-page: https://gitlab.com/4degrees/plectrum
Author: Martin Pengelly-Phillips
Author-email: martin@4degrees.ltd.uk
License: Apache License (2.0)
Keywords: terminal,gui,selector
Platform: UNKNOWN
Requires-Dist: ordered-set (<3,>=2)
Requires-Dist: prompt-toolkit (>=1.0.9,<2)
Provides-Extra: dev
Requires-Dist: lowdown (>=0.1.0,<1); extra == 'dev'
Requires-Dist: pytest (<3,>=2.3.5); extra == 'dev'
Requires-Dist: pytest-cov (<3,>=2); extra == 'dev'
Requires-Dist: pytest-mock (>=0.11,<1); extra == 'dev'
Requires-Dist: pytest-runner (>=2.7,<3); extra == 'dev'
Requires-Dist: sphinx (>=1.2.2,<2); extra == 'dev'
Requires-Dist: sphinx-rtd-theme (>=0.1.6,<1); extra == 'dev'
Provides-Extra: doc
Requires-Dist: lowdown (>=0.1.0,<1); extra == 'doc'
Requires-Dist: sphinx (>=1.2.2,<2); extra == 'doc'
Requires-Dist: sphinx-rtd-theme (>=0.1.6,<1); extra == 'doc'
Provides-Extra: test
Requires-Dist: pytest (<3,>=2.3.5); extra == 'test'
Requires-Dist: pytest-cov (<3,>=2); extra == 'test'
Requires-Dist: pytest-mock (>=0.11,<1); extra == 'test'
Requires-Dist: pytest-runner (>=2.7,<3); extra == 'test'
